README.txt
collective.zodbbrowser-configure.zcml
setup.cfg
setup.py
collective/__init__.py
collective.zodbbrowser.egg-info/PKG-INFO
collective.zodbbrowser.egg-info/SOURCES.txt
collective.zodbbrowser.egg-info/dependency_links.txt
collective.zodbbrowser.egg-info/entry_points.txt
collective.zodbbrowser.egg-info/namespace_packages.txt
collective.zodbbrowser.egg-info/not-zip-safe
collective.zodbbrowser.egg-info/paster_plugins.txt
collective.zodbbrowser.egg-info/requires.txt
collective.zodbbrowser.egg-info/top_level.txt
collective/zodbbrowser/README.txt
collective/zodbbrowser/__init__.py
collective/zodbbrowser/bottom.py
collective/zodbbrowser/configure.zcml
collective/zodbbrowser/interfaces.py
collective/zodbbrowser/left.py
collective/zodbbrowser/right.py
collective/zodbbrowser/tests.py
collective/zodbbrowser/utils.py
collective/zodbbrowser/version.txt
collective/zodbbrowser/resources/jquery.cookie.js
collective/zodbbrowser/resources/jquery.dynatree.js
collective/zodbbrowser/resources/jquery.layout.min.js
collective/zodbbrowser/resources/loading.gif
collective/zodbbrowser/resources/sourcecode.css
collective/zodbbrowser/resources/zodbbrowser.css
collective/zodbbrowser/resources/zodbbrowser.js
collective/zodbbrowser/resources/zodblogo.png
collective/zodbbrowser/resources/dynatree/icons.gif
collective/zodbbrowser/resources/dynatree/jquery.dynatree.js
collective/zodbbrowser/resources/dynatree/loading.gif
collective/zodbbrowser/resources/dynatree/ui.dynatree.css
collective/zodbbrowser/resources/dynatree/vline.gif
collective/zodbbrowser/templates/zodbbrowser.zpt
docs/HISTORY.txt
docs/INSTALL.txt
docs/LICENSE.GPL
docs/LICENSE.txt