Metadata-Version: 1.0
Name: collective.zodbbrowser
Version: 0.1
Summary: A zodb browser for Zope2
Home-page: http://code.google.com/p/zodbbrowser
Author: Roberto Allende - Menttes SRL
Author-email: rover@menttes.com
License: GPL
Keywords: zope2 zope zodb python plone
Platform: UNKNOWN
Classifier: Framework :: Plone
Classifier: Programming Language :: Python
